{
	"class" : {
		"URIRegex" : "mf 6/24/2021 12:00",
		"closeCharacter" : "jh 6/24/2021 13:45",
		"delimiterTypes" : "mf 6/23/2021 15:59",
		"emailRegex" : "mf 6/24/2021 12:02",
		"newWith:and:" : "jh 7/28/2021 16:03" },
	"instance" : {
		"=" : "jh 7/28/2021 16:02",
		"applyStylingWith:" : "jh 7/28/2021 16:02",
		"autolinkPath" : "jh 7/28/2021 16:02",
		"autolinkPath:" : "jh 7/28/2021 16:05",
		"beEmail" : "jh 6/23/2021 12:20",
		"beNotEmail" : "jh 6/23/2021 12:20",
		"convertWith:" : "jh 7/28/2021 16:03",
		"extractString" : "jh 7/28/2021 16:22",
		"hash" : "jh 7/28/2021 16:03",
		"htmlClosingTag" : "jh 6/25/2021 12:06",
		"htmlOpeningTag" : "jh 7/28/2021 16:03",
		"initialize" : "jh 6/23/2021 12:22",
		"isEmail" : "jh 6/24/2021 12:44",
		"lastChar" : "jh 7/11/2021 11:25",
		"textAttributes" : "jh 7/28/2021 16:03",
		"totalLength" : "jh 7/28/2021 16:03",
		"treeRepresentation" : "jh 7/28/2021 16:03" } }
