{
	"class" : {
		"<=" : "jko 5/6/2019 14:49",
		"beginsWith:" : "kgr 5/9/2019 16:39",
		"newFor:" : "fgo 5/10/2019 15:26",
		"precedence" : "jko 5/6/2019 14:45" },
	"instance" : {
		"asStringToken" : "jko 5/16/2019 16:56",
		"content" : "fgo 5/4/2019 14:53",
		"content:" : "fgo 4/29/2019 14:44",
		"endPosition" : "fgo 5/10/2019 15:22",
		"initialize:" : "jko 5/6/2019 14:35",
		"isDelimiter" : "fgo 4/29/2019 14:40",
		"length" : "jko 5/6/2019 14:36",
		"position" : "fgo 4/29/2019 14:21",
		"position:" : "fgo 4/29/2019 14:21" } }
